dyff/audit/__init__.py
dyff/audit/_version.py
dyff/audit/dynamic_import.py
dyff/audit/workflows.py
dyff/audit/_internal/__init__.py
dyff/audit/_internal/timestamp.py
dyff/audit/analysis/__init__.py
dyff/audit/analysis/context.py
dyff/audit/analysis/jupyter.py
dyff/audit/analysis/legacy.py
dyff/audit/analysis/python.py
dyff/audit/analysis/runners.py
dyff/audit/components/__init__.py
dyff/audit/components/templates/Conclusion.template.html
dyff/audit/components/templates/Score.template.html
dyff/audit/components/templates/TitleCard.template.html
dyff/audit/components/templates/__init__.py
dyff/audit/data/__init__.py
dyff/audit/data/text.py
dyff/audit/local/__init__.py
dyff/audit/local/mocks.py
dyff/audit/local/platform.py
dyff/audit/metrics/__init__.py
dyff/audit/metrics/base.py
dyff/audit/metrics/text.py
dyff/audit/scoring/__init__.py
dyff/audit/scoring/base.py
dyff/audit/scoring/classification.py
dyff/audit/scoring/example.py
dyff/audit/scoring/text.py
dyff_audit-0.16.8.dist-info/licenses/LICENSE
dyff_audit-0.16.8.dist-info/licenses/NOTICE
dyff_audit-0.16.8.dist-info/METADATA
dyff_audit-0.16.8.dist-info/WHEEL
dyff_audit-0.16.8.dist-info/top_level.txt
dyff_audit-0.16.8.dist-info/RECORD
