Metadata-Version: 2.4
Name: dyff-audit
Version: 0.16.8
Summary: Audit tools for the Dyff AI auditing platform.
Author-email: Digital Safety Research Institute <contact@dsri.org>
License: Apache-2.0
Project-URL: Home, https://gitlab.com/dyff/packages/dyff-audit
Project-URL: Issues, https://gitlab.com/dyff/packages/dyff-audit/-/issues
Keywords: ai,audit,safety,evaluation
Classifier: Development Status :: 3 - Alpha
Classifier: Intended Audience :: Science/Research
Classifier: License :: OSI Approved :: Apache Software License
Classifier: Operating System :: OS Independent
Classifier: Programming Language :: Python :: 3
Classifier: Programming Language :: Python :: 3.10
Classifier: Programming Language :: Python :: 3.11
Classifier: Programming Language :: Python :: 3.12
Classifier: Topic :: Scientific/Engineering :: Artificial Intelligence
Requires-Python: >=3.10
License-File: LICENSE
License-File: NOTICE
Requires-Dist: dyff-client>=0.23.8
Requires-Dist: dyff-schema>=0.40.1
Requires-Dist: beautifulsoup4
Requires-Dist: lxml
Requires-Dist: nbconvert
Requires-Dist: nbformat
Requires-Dist: notebook
Requires-Dist: numpy<2
Requires-Dist: pandas
Requires-Dist: pyarrow
Requires-Dist: pydantic<3.0.0,>=2.0.0
Requires-Dist: ruamel.yaml
Provides-Extra: dev
Requires-Dist: docker; extra == "dev"
Requires-Dist: pytest; extra == "dev"
Requires-Dist: pytest-datafiles; extra == "dev"
Requires-Dist: pytest-depends; extra == "dev"
Dynamic: license-file
